{
  "id": 1220,
  "nome": "Domicílios particulares permanentes com acesso à Internet",
  "URL": "https://sidra.ibge.gov.br/tabela/1220",
  "pesquisa": "Indicadores de Desenvolvimento Sustentável",
  "assunto": "Acesso à internet",
  "periodicidade": {
    "frequencia": "anual",
    "inicio": 2005,
    "fim": 2011
  },
  "nivelTerritorial": {
    "Administrativo": [
      "N1",
      "N2",
      "N3"
    ],
    "Especial": [],
    "IBGE": []
  },
  "variaveis": [
    {
      "id": 96,
      "nome": "Domicílios particulares permanentes",
      "unidade": "Mil unidades",
      "sumarizacao": []
    },
    {
      "id": 2583,
      "nome": "Domicílios particulares permanentes com acesso à internet",
      "unidade": "Mil unidades",
      "sumarizacao": []
    },
    {
      "id": 2584,
      "nome": "Percentual de domicílios particulares permanentes com acesso à internet",
      "unidade": "%",
      "sumarizacao": []
    }
  ],
  "classificacoes": []
}