{
  "id": 2041,
  "nome": "Pessoas, total, economicamente ativas e não economicamente ativas na semana de referência por grupos de idade",
  "URL": "https://sidra.ibge.gov.br/tabela/2041",
  "pesquisa": "Pesquisa Mensal de Emprego",
  "assunto": "Emprego",
  "periodicidade": {
    "frequencia": "mensal",
    "inicio": 200203,
    "fim": 201602
  },
  "nivelTerritorial": {
    "Administrativo": [
      "N7"
    ],
    "Especial": [],
    "IBGE": [
      "N110"
    ]
  },
  "variaveis": [
    {
      "id": 890,
      "nome": "Pessoas",
      "unidade": "Mil pessoas",
      "sumarizacao": [
        "nivelTerritorial"
      ]
    },
    {
      "id": 1000890,
      "nome": "Pessoas - percentual do total geral",
      "unidade": "%",
      "sumarizacao": []
    },
    {
      "id": 893,
      "nome": "Coeficiente de variação - Pessoas",
      "unidade": "Coeficiente",
      "sumarizacao": []
    },
    {
      "id": 891,
      "nome": "Pessoas economicamente ativas na semana de referência",
      "unidade": "Mil pessoas",
      "sumarizacao": [
        "nivelTerritorial"
      ]
    },
    {
      "id": 1000891,
      "nome": "Pessoas economicamente ativas na semana de referência - percentual do total geral",
      "unidade": "%",
      "sumarizacao": []
    },
    {
      "id": 894,
      "nome": "Coeficiente de variação - Pessoas economicamente ativas na semana de referência",
      "unidade": "Coeficiente",
      "sumarizacao": []
    },
    {
      "id": 892,
      "nome": "Pessoas não economicamente ativas na semana de referência",
      "unidade": "Mil pessoas",
      "sumarizacao": [
        "nivelTerritorial"
      ]
    },
    {
      "id": 1000892,
      "nome": "Pessoas não economicamente ativas na semana de referência - percentual do total geral",
      "unidade": "%",
      "sumarizacao": []
    },
    {
      "id": 895,
      "nome": "Coeficiente de variação - Pessoas não economicamente ativas na semana de referência",
      "unidade": "Coeficiente",
      "sumarizacao": []
    }
  ],
  "classificacoes": [
    {
      "id": 58,
      "nome": "Grupo de idade",
      "sumarizacao": {
        "status": true,
        "excecao": [
          893,
          894,
          895
        ]
      },
      "categorias": [
        {
          "id": 0,
          "nome": "Total",
          "unidade": null,
          "nivel": 0
        },
        {
          "id": 1142,
          "nome": "10 a 14 anos",
          "unidade": null,
          "nivel": 1
        },
        {
          "id": 2792,
          "nome": "15 a 17 anos",
          "unidade": null,
          "nivel": 1
        },
        {
          "id": 100052,
          "nome": "18 a 24 anos",
          "unidade": null,
          "nivel": 1
        },
        {
          "id": 100053,
          "nome": "25 a 49 anos",
          "unidade": null,
          "nivel": 1
        },
        {
          "id": 5502,
          "nome": "50 anos ou mais",
          "unidade": null,
          "nivel": 1
        }
      ]
    }
  ]
}