{
  "id": 2432,
  "nome": "Domicílios particulares permanentes por número de famílias, situação do domicílio e adequação da moradia",
  "URL": "https://sidra.ibge.gov.br/tabela/2432",
  "pesquisa": "Censo Demográfico",
  "assunto": "Domicílios",
  "periodicidade": {
    "frequencia": "anual",
    "inicio": 2000,
    "fim": 2000
  },
  "nivelTerritorial": {
    "Administrativo": [
      "N1",
      "N2",
      "N8",
      "N9",
      "N6",
      "N14",
      "N7",
      "N13",
      "N3"
    ],
    "Especial": [],
    "IBGE": []
  },
  "variaveis": [
    {
      "id": 96,
      "nome": "Domicílios particulares permanentes",
      "unidade": "Unidades",
      "sumarizacao": []
    },
    {
      "id": 1000096,
      "nome": "Domicílios particulares permanentes - percentual do total geral",
      "unidade": "%",
      "sumarizacao": []
    }
  ],
  "classificacoes": [
    {
      "id": 197,
      "nome": "Número de famílias",
      "sumarizacao": {
        "status": true,
        "excecao": []
      },
      "categorias": [
        {
          "id": 0,
          "nome": "Total",
          "unidade": null,
          "nivel": 0
        },
        {
          "id": 104552,
          "nome": "Uma família",
          "unidade": null,
          "nivel": 1
        },
        {
          "id": 104553,
          "nome": "Mais de uma família",
          "unidade": null,
          "nivel": 1
        }
      ]
    },
    {
      "id": 1,
      "nome": "Situação do domicílio",
      "sumarizacao": {
        "status": true,
        "excecao": []
      },
      "categorias": [
        {
          "id": 0,
          "nome": "Total",
          "unidade": null,
          "nivel": 0
        },
        {
          "id": 1,
          "nome": "Urbana",
          "unidade": null,
          "nivel": 1
        },
        {
          "id": 2,
          "nome": "Rural",
          "unidade": null,
          "nivel": 1
        }
      ]
    },
    {
      "id": 12236,
      "nome": "Adequação da moradia",
      "sumarizacao": {
        "status": true,
        "excecao": []
      },
      "categorias": [
        {
          "id": 0,
          "nome": "Total",
          "unidade": null,
          "nivel": 0
        },
        {
          "id": 104567,
          "nome": "Adequada",
          "unidade": null,
          "nivel": 1
        },
        {
          "id": 104568,
          "nome": "Semi-adequada",
          "unidade": null,
          "nivel": 1
        },
        {
          "id": 104569,
          "nome": "Inadequada",
          "unidade": null,
          "nivel": 1
        }
      ]
    }
  ]
}