{
  "id": 4037,
  "nome": "Pessoas de 15 anos ou mais de idade, ocupadas na semana de referência, por número de trabalhos, sexo e associação a sindicatos",
  "URL": "https://sidra.ibge.gov.br/tabela/4037",
  "pesquisa": "Pesquisa Nacional por Amostra de Domicílios",
  "assunto": "Trabalho e rendimento",
  "periodicidade": {
    "frequencia": "anual",
    "inicio": 2012,
    "fim": 2015
  },
  "nivelTerritorial": {
    "Administrativo": [
      "N1",
      "N2",
      "N7",
      "N3"
    ],
    "Especial": [],
    "IBGE": []
  },
  "variaveis": [
    {
      "id": 1139,
      "nome": "Pessoas de 15 anos ou mais de idade, ocupadas na semana de referência",
      "unidade": "Mil pessoas",
      "sumarizacao": []
    },
    {
      "id": 1001139,
      "nome": "Pessoas de 15 anos ou mais de idade, ocupadas na semana de referência - percentual do total geral",
      "unidade": "%",
      "sumarizacao": []
    }
  ],
  "classificacoes": [
    {
      "id": 12031,
      "nome": "Número de trabalhos",
      "sumarizacao": {
        "status": true,
        "excecao": []
      },
      "categorias": [
        {
          "id": 0,
          "nome": "Total",
          "unidade": null,
          "nivel": 0
        },
        {
          "id": 99209,
          "nome": "1 trabalho",
          "unidade": null,
          "nivel": 1
        },
        {
          "id": 99210,
          "nome": "2 ou mais trabalhos",
          "unidade": null,
          "nivel": 1
        }
      ]
    },
    {
      "id": 2,
      "nome": "Sexo",
      "sumarizacao": {
        "status": true,
        "excecao": []
      },
      "categorias": [
        {
          "id": 0,
          "nome": "Total",
          "unidade": null,
          "nivel": 0
        },
        {
          "id": 92956,
          "nome": "Homem",
          "unidade": null,
          "nivel": 1
        },
        {
          "id": 92957,
          "nome": "Mulher",
          "unidade": null,
          "nivel": 1
        }
      ]
    },
    {
      "id": 12032,
      "nome": "Associação a sindicatos",
      "sumarizacao": {
        "status": true,
        "excecao": []
      },
      "categorias": [
        {
          "id": 0,
          "nome": "Total",
          "unidade": null,
          "nivel": 0
        },
        {
          "id": 99211,
          "nome": "Associadas",
          "unidade": null,
          "nivel": 1
        },
        {
          "id": 99212,
          "nome": "Não associadas",
          "unidade": null,
          "nivel": 1
        }
      ]
    }
  ]
}