{
  "id": 6690,
  "nome": "Indicador 12.1.1 - Existência de Plano de Produção e Consumo Sustentável",
  "URL": "https://sidra.ibge.gov.br/tabela/6690",
  "pesquisa": "Objetivos de Desenvolvimento Sustentável",
  "assunto": "Consumo alimentar",
  "periodicidade": {
    "frequencia": "anual",
    "inicio": 2002,
    "fim": 2019
  },
  "nivelTerritorial": {
    "Administrativo": [
      "N1"
    ],
    "Especial": [],
    "IBGE": []
  },
  "variaveis": [
    {
      "id": 9620,
      "nome": "Existência de Plano de Produção e Consumo Sustentável",
      "unidade": "Nenhuma",
      "sumarizacao": []
    }
  ],
  "classificacoes": []
}