{
  "id": 8505,
  "nome": "Pessoas de 15 anos ou mais de idade que foram vítimas de roubo nos últimos 12 meses, por cor ou raça",
  "URL": "https://sidra.ibge.gov.br/tabela/8505",
  "pesquisa": "Pesquisa Nacional por Amostra de Domicílios Contínua anual",
  "assunto": "Furto e roubo",
  "periodicidade": {
    "frequencia": "anual",
    "inicio": 2021,
    "fim": 2021
  },
  "nivelTerritorial": {
    "Administrativo": [
      "N1",
      "N2"
    ],
    "Especial": [],
    "IBGE": []
  },
  "variaveis": [
    {
      "id": 12452,
      "nome": "Pessoas de 15 anos ou mais de idade que foram vítimas de roubo nos últimos 12 meses",
      "unidade": "Mil pessoas",
      "sumarizacao": []
    },
    {
      "id": 12453,
      "nome": "Coeficiente de variação - Pessoas de 15 anos ou mais de idade que foram vítimas de roubo nos últimos 12 meses",
      "unidade": "%",
      "sumarizacao": []
    },
    {
      "id": 12573,
      "nome": "Distribuição percentual das pessoas de 15 anos ou mais de idade que foram vítimas de roubo nos últimos 12 meses",
      "unidade": "%",
      "sumarizacao": []
    },
    {
      "id": 12574,
      "nome": "Coeficiente de variação - Distribuição percentual das pessoas de 15 anos ou mais de idade que foram vítimas de roubo nos últimos 12 meses",
      "unidade": "%",
      "sumarizacao": []
    }
  ],
  "classificacoes": [
    {
      "id": 86,
      "nome": "Cor ou raça",
      "sumarizacao": {
        "status": true,
        "excecao": []
      },
      "categorias": [
        {
          "id": 95251,
          "nome": "Total",
          "unidade": null,
          "nivel": 0
        },
        {
          "id": 2776,
          "nome": "Branca",
          "unidade": null,
          "nivel": 1
        },
        {
          "id": 2777,
          "nome": "Preta",
          "unidade": null,
          "nivel": 1
        },
        {
          "id": 2779,
          "nome": "Parda",
          "unidade": null,
          "nivel": 1
        }
      ]
    }
  ]
}